inkscape_svg_layer_extractor/__init__.py
inkscape_svg_layer_extractor/__main__.py
inkscape_svg_layer_extractor/inkscape_svg_layer_extractor.py
inkscape_svg_layer_extractor-0.0.2.dist-info/LICENSE
inkscape_svg_layer_extractor-0.0.2.dist-info/METADATA
inkscape_svg_layer_extractor-0.0.2.dist-info/WHEEL
inkscape_svg_layer_extractor-0.0.2.dist-info/top_level.txt
inkscape_svg_layer_extractor-0.0.2.dist-info/RECORD
