Metadata-Version: 2.1
Name: inkscape-svg-layer-extractor
Version: 0.0.2
Summary: Small script to extract layers from inscape svg
Home-page: https://github.com/twyleg
Author: Torsten Wylegala
Author-email: mail@twyleg.de
License: GPL 3.0
Keywords: inkscape svg layer extractor
Platform: UNKNOWN
License-File: LICENSE
